{
    "description": "Ви підходите до кентавра і вам потрібно вирішити як діяти далі. Як клірик, ви можете запропонувати йому очистити свою душу на сповіді та віднайти спокій. Ви не перший раз проводите такі сеанси та знаєте як змусити чоловіків плакати.  А можете просто чесно попросити одненьку сльозу.",
    "ansvers":  {
        "ansver1": ["Запевнити кентавра, що йому потрібна сповідь", "Hotel_quest", "alchemist30", "alchemist30_choice1.json"],
        "ansver2": ["Просто пояснити йому всю ситуацію", "Hotel_quest", "alchemist30", "alchemist30_choice2.json"]
    },

    "items": {
        "folse_phoenix": [
            "False",
            "Перо"
        ],
        "phoenix": [
            "False",
            "Перо фенікса"
        ],
        "dew": [
            "False",
            "Кришталева роса"
        ],
        "tears": [
            "False",
            "Слізка кентавра"
        ]
    },
    "interlocutor": [
        "Character",
        "additional_characters",
        "centaur.png"
    ]
}
    