{
    "description": "Аліанд  прийшов до вашого кабінету відразу ж, як ви його викликали. Ельф докладно розповів вам про подію у парку:- Зранку я прямував до посольства, я завжди скорочую свій шлях через парк, бо не люблю ці смердючі людські вулиці.  Я був приблизно за хвилину ходьби від західного входу до парку, коли пролунали сигнали тривоги. Тоді я не надав цьому особливого значення і продовжив свій шлях. Незабаром мене наздогнала незнайома жінка, яка запитала мене, що сталося. Я сказав, що я не знаю. Майже одразу ж з'явився капітан Дерая. Він сказав, що сталося вбивство, і наказав усім слідувати за ним. Тіло вбитого лежало в заростях кущів приблизно за тридцять метрів від того місця, де ми стояли. Ніхто з нас не зізнався, що знав убитого чи зустрічав його колись раніше.",
    "ansvers":  {
        "ansver1": ["Розкажи мені, про\n вирощування енару у\n посольстві ельфів", "Murder_in_city", "castle66", "castle66_choice1.json"],
        "ansver2": ["Розкажи мені про\n себе детальніше", "Murder_in_city", "castle66", "castle66_choice2.json"]
    },

    "items": {
        "none": "False"
    }
}
    