{
    "description": "Мати дівчинки повела її до кімнати, а ви з Менаріусом пішли на галявину, де вже починалось свято. Чим ближче ви підходили, то голосніше чули музику. Таємничі звуки дзвонів та флейти мішаються зі співами вітру і шепітами лісу, створюючи музичну гармонію, яка зачаровує всіх, хто прийшов на цю святкову галявину. Лісові Духи, у цьому морі квітів та живих ілюзій, втілюються в цих звуках, роблячи своє свято чарівним і незабутнім. Ця галявина – це місце, де природа живе і дихає, а її душа відкривається у величезному вогнищі та магії, що заповнює повітря. Вам одразу дали в руки келих амброзії - магічного напою, який можна спробувати тільки на такому святі. Ви пили, танцювали та співали разом з усіма іншими, почуття єдності та причетності до чогось великого переповнювали вас. Це була найкраща ніч у вашому житті, але ви не встигли виконати завдання.",
    "ansvers":  {
        "ansver1": ["", ""],
        "ansver2": ["", ""]
    },

    "items": {
        "folse_phoenix": [
            "False",
            "Перо"
        ],
        "phoenix": [
            "False",
            "Перо фенікса"
        ],
        "dew": [
            "False",
            "Кришталева роса"
        ],
        "tears": [
            "False",
            "Слізка кентавра"
        ]
    },
    "interlocutor": []
}
    