{
    "description": "Коли ви ідете по коридору, ваш погляд відразу ж зупиняється: на вашому шляху стоїть Валеріан Мудрий найвидатніший лицар у вашому королівстві. Ви не бачите його обличчя, бо його закриває шолом і весь він одягнений у повний обладунок. Але ви точно знаєте, що це він, адже у вас вдома є багато афіш та портретів з цим лицарем, він з самого дитинства був вашим героєм ви напам'ять знаєте всі ці ковані елементи на його рукавицях, витончені візерунки на нагруднику. Коли ви підходите ближче, чуєте голос з під шолома: 'Привіт друже, допоможеш мені дійти до кімнати та вибратись з цього обладунку?'",
    "ansvers":  {
        "ansver1": ["Звичайно, погодитись", "Hotel_quest", "alchemist39", "alchemist39_choice1.json"],
        "ansver2": ["Відмовитись та іти на кухню", "Hotel_quest", "alchemist39", "alchemist39_choice2.json"]
    },

    "items": {
        "folse_phoenix": [
            "False",
            "Перо"
        ],
        "phoenix": [
            "False",
            "Перо фенікса"
        ],
        "dew": [
            "False",
            "Кришталева роса"
        ],
        "tears": [
            "False",
            "Слізка кентавра"
        ]
    },
    "interlocutor": [
        "Character",
        "additional_characters",
        "knight.png"
    ]
}
    